lineparser.cp37-win_amd64.pyd
lineparser-0.0.0.dev7.dist-info/LICENSE
lineparser-0.0.0.dev7.dist-info/METADATA
lineparser-0.0.0.dev7.dist-info/WHEEL
lineparser-0.0.0.dev7.dist-info/top_level.txt
lineparser-0.0.0.dev7.dist-info/RECORD
