Metadata-Version: 2.1
Name: lineparser
Version: 0.0.0.dev7
Summary: Fast parser for fixed-column line data files
Home-page: https://github.com/jkarns275/lineparser
Author: Joshua Karns
Author-email: jkarns275@gmail.com
License: MIT
Platform: UNKNOWN
Classifier: Development Status :: 3 - Alpha
Classifier: License :: OSI Approved :: MIT License
Classifier: Programming Language :: Python :: 3
